dcm2mids/__init__.py
dcm2mids/__main__.py
dcm2mids/create_mids_directory.py
dcm2mids/generate_tsvs.py
dcm2mids/get_dicomdir.py
dcm2mids/tagger.py
dcm2mids/logger/__init__.py
dcm2mids/logger/logger.py
dcm2mids/procedures/__init__.py
dcm2mids/procedures/dicom2nifti.py
dcm2mids/procedures/dicom2png.py
dcm2mids/procedures/dictify.py
dcm2mids/procedures/procedures.py
dcm2mids/procedures/electrical_activity/__init__.py
dcm2mids/procedures/general_radiology/__init__.py
dcm2mids/procedures/general_radiology/conventional_radiology_procedure.py
dcm2mids/procedures/general_radiology/tomography_procedure.py
dcm2mids/procedures/magnetic_resonance/__init__.py
dcm2mids/procedures/magnetic_resonance/magnetic_resonance_procedure.py
dcm2mids/procedures/nuclear_medicine/__init__.py
dcm2mids/procedures/ultrasound/__init__.py
dcm2mids/procedures/visible_light/__init__.py
dcm2mids/procedures/visible_light/microscopy_procedure.py
dcm2mids/procedures/visible_light/ophthalmography_procedure.py
dcm2mids-0.2.20240725.dist-info/LICENSE.txt
dcm2mids-0.2.20240725.dist-info/METADATA
dcm2mids-0.2.20240725.dist-info/WHEEL
dcm2mids-0.2.20240725.dist-info/top_level.txt
dcm2mids-0.2.20240725.dist-info/RECORD
